sqlconnect/__init__.py
sqlconnect/config.py
sqlconnect/connector.py
sqlconnect-0.3.2.dist-info/METADATA
sqlconnect-0.3.2.dist-info/WHEEL
sqlconnect-0.3.2.dist-info/licenses/LICENCE
sqlconnect-0.3.2.dist-info/RECORD
