Metadata-Version: 2.1
Name: sqlconnect
Version: 0.3.2
Summary: Simplifies connections to SQL databases for data analysts. Populate DataFrames with the results of queries directly from .sql files.
Project-URL: Homepage, https://github.com/JustinFrizzell/sqlconnect
Project-URL: Documentation, https://sqlconnect.readthedocs.io/en/latest/
Author: Justin Frizzell
License: MIT License
License-File: LICENCE
Keywords: SQL,configuration,connection,database
Classifier: Intended Audience :: Developers
Classifier: License :: OSI Approved :: MIT License
Classifier: Topic :: Database
Requires-Python: >=3.8
Requires-Dist: oracledb>=2.0.0
Requires-Dist: pandas>=2.0.0
Requires-Dist: psycopg2-binary>=2.0.0
Requires-Dist: pymysql>=1.0.0
Requires-Dist: pyodbc>=5.0.0
Requires-Dist: python-dotenv>=1.0.0
Requires-Dist: pyyaml>=6.0.0
Requires-Dist: sqlalchemy>=2.0.0
Provides-Extra: dev
Requires-Dist: build>1.0.0; extra == 'dev'
Requires-Dist: pytest>=7.0.0; extra == 'dev'
Requires-Dist: ruff>=0.3.0; extra == 'dev'
Requires-Dist: twine>=5.0.0; extra == 'dev'
